odoo/addons/l10n_br_account_nfe/README.rst
odoo/addons/l10n_br_account_nfe/__init__.py
odoo/addons/l10n_br_account_nfe/__manifest__.py
odoo/addons/l10n_br_account_nfe/hooks.py
odoo/addons/l10n_br_account_nfe/demo/account_invoice_sn_demo.xml
odoo/addons/l10n_br_account_nfe/i18n/l10n_br_account_nfe.pot
odoo/addons/l10n_br_account_nfe/i18n/pt_BR.po
odoo/addons/l10n_br_account_nfe/models/__init__.py
odoo/addons/l10n_br_account_nfe/models/account_move.py
odoo/addons/l10n_br_account_nfe/models/account_payment_mode.py
odoo/addons/l10n_br_account_nfe/models/document.py
odoo/addons/l10n_br_account_nfe/models/leiauteNFe.py
odoo/addons/l10n_br_account_nfe/readme/CONFIGURE.md
odoo/addons/l10n_br_account_nfe/readme/CONTRIBUTORS.md
odoo/addons/l10n_br_account_nfe/readme/DESCRIPTION.md
odoo/addons/l10n_br_account_nfe/readme/HISTORY.md
odoo/addons/l10n_br_account_nfe/readme/ROADMAP.md
odoo/addons/l10n_br_account_nfe/readme/USAGE.md
odoo/addons/l10n_br_account_nfe/report/__init__.py
odoo/addons/l10n_br_account_nfe/report/danfe_report.xml
odoo/addons/l10n_br_account_nfe/report/ir_actions_report.py
odoo/addons/l10n_br_account_nfe/static/description/icon.png
odoo/addons/l10n_br_account_nfe/static/description/index.html
odoo/addons/l10n_br_account_nfe/tests/__init__.py
odoo/addons/l10n_br_account_nfe/tests/test_invoice_refund.py
odoo/addons/l10n_br_account_nfe/tests/test_nfce_contingency.py
odoo/addons/l10n_br_account_nfe/tests/test_nfe_danfe_account.py
odoo/addons/l10n_br_account_nfe/tests/test_nfe_generate_tags_cobr_dup_pag.py
odoo/addons/l10n_br_account_nfe/tests/test_nfe_import.py
odoo/addons/l10n_br_account_nfe/tests/test_nfe_with_ipi.py
odoo/addons/l10n_br_account_nfe/tests/nfe/35231149647316000169550010000661061151600085-nfe.xml
odoo/addons/l10n_br_account_nfe/views/account_payment_mode.xml
odoo/addons/l10n_br_account_nfe/wizard/__init__.py
odoo/addons/l10n_br_account_nfe/wizard/account_move_reversal.py
odoo/addons/l10n_br_account_nfe/wizard/account_move_reversal_view.xml
odoo_addon_l10n_br_account_nfe-16.0.8.0.0.dist-info/METADATA
odoo_addon_l10n_br_account_nfe-16.0.8.0.0.dist-info/WHEEL
odoo_addon_l10n_br_account_nfe-16.0.8.0.0.dist-info/top_level.txt
odoo_addon_l10n_br_account_nfe-16.0.8.0.0.dist-info/RECORD
