Metadata-Version: 2.1
Name: odoo-addon-l10n_br_account_nfe
Version: 16.0.8.0.0
Requires-Python: >=3.10
Requires-Dist: odoo-addon-account_payment_partner>=16.0dev,<16.1dev
Requires-Dist: odoo-addon-l10n_br_account>=16.0dev,<16.1dev
Requires-Dist: odoo-addon-l10n_br_account_due_list>=16.0dev,<16.1dev
Requires-Dist: odoo-addon-l10n_br_nfe>=16.0dev,<16.1dev
Requires-Dist: odoo>=16.0a,<16.1dev
Summary: Integration between l10n_br_account and l10n_br_nfe
Home-page: https://github.com/OCA/l10n-brazil
License: AGPL-3
Author: Engenere,Akretion,Odoo Community Association (OCA)
Author-email: support@odoo-community.org
Classifier: Programming Language :: Python
Classifier: Framework :: Odoo
Classifier: Framework :: Odoo :: 16.0
Classifier: License :: OSI Approved :: GNU Affero General Public License v3
Classifier: Development Status :: 4 - Beta
